setup.cfg
setup.py
axel/__init__.py
axel_wrapper.egg-info/PKG-INFO
axel_wrapper.egg-info/SOURCES.txt
axel_wrapper.egg-info/dependency_links.txt
axel_wrapper.egg-info/top_level.txt