Metadata-Version: 1.0
Name: axel-wrapper
Version: 0.0.1
Summary: Python wrapper of axel, a light command line download accelerator
Home-page: https://github.com/yozel/axel-wrapper
Author: Yasin Ozel
Author-email: me@yozel.co
License: GPL3
Platform: UNKNOWN
